retrotype/__init__.py
retrotype/char_maps.py
retrotype/retrotype_cli.py
retrotype/retrotype_lib.py
retrotype-1.1.0.dist-info/LICENSE
retrotype-1.1.0.dist-info/METADATA
retrotype-1.1.0.dist-info/WHEEL
retrotype-1.1.0.dist-info/entry_points.txt
retrotype-1.1.0.dist-info/top_level.txt
retrotype-1.1.0.dist-info/RECORD
