Metadata-Version: 2.1
Name: retrotype
Version: 1.1.0
Summary: Debuging and conversion tool for 1980s magazine type-in programs
Author-email: Michael Buhidar <mbuhidar@gmail.com>
License: MIT License
Project-URL: Homepage, https://github.com/mbuhidar/retrotype
Keywords: commodore64,vic20,commodore,atari,compute,ahoy,run,magazine,c64
Classifier: License :: OSI Approved :: MIT License
Classifier: Programming Language :: Python :: 3
Classifier: Programming Language :: Python :: 3 :: Only
Classifier: Programming Language :: Python :: Implementation :: CPython
Requires-Python: >=3.8
License-File: LICENSE
Provides-Extra: dev
Requires-Dist: flake8 ; extra == 'dev'
Requires-Dist: mypy ; extra == 'dev'
Requires-Dist: black ; extra == 'dev'
Requires-Dist: pre-commit ; extra == 'dev'
Provides-Extra: test
Requires-Dist: pytest ; extra == 'test'
Requires-Dist: coverage ; extra == 'test'
